Metadata-Version: 1.0
Name: crank-nicolson-numba
Version: 0.0.6
Summary: A numba implementation of Crank-Nicolson
Home-page: https://github.com/carlidel/crank_nicolson_numba
Author: Carlo Emilio Montanari
Author-email: carlidel95@gmail.com
License: MIT
Platform: UNKNOWN
